odoo_mcp/__init__.py
odoo_mcp/__main__.py
odoo_mcp/extensions.py
odoo_mcp/models.py
odoo_mcp/odoo_client.py
odoo_mcp/prompts.py
odoo_mcp/resources.py
odoo_mcp/server.py
odoo_mcp/tools_accounting.py
odoo_mcp/tools_inventory.py
odoo_mcp/tools_purchase.py
odoo_mcp/tools_sales.py
odoo_mcp_improved-1.0.5.dist-info/licenses/LICENSE
odoo_mcp_improved-1.0.5.dist-info/METADATA
odoo_mcp_improved-1.0.5.dist-info/WHEEL
odoo_mcp_improved-1.0.5.dist-info/entry_points.txt
odoo_mcp_improved-1.0.5.dist-info/top_level.txt
odoo_mcp_improved-1.0.5.dist-info/RECORD
