Metadata-Version: 2.4
Name: odoo-mcp-improved
Version: 1.0.5
Summary: MCP Server for Odoo Integration
Author-email: Yhasmani Valdes <yhasmanivm@gmail.com>
License: MIT
Project-URL: Homepage, https://github.com/hachecito/odoo-mcp-improved
Project-URL: Issues, https://github.com/hachecito/odoo-mcp-improved/issues
Keywords: odoo,mcp,server,ai
Classifier: License :: OSI Approved :: MIT License
Classifier: Programming Language :: Python :: 3
Classifier: Programming Language :: Python :: 3.10
Classifier: Operating System :: OS Independent
Requires-Python: >=3.10
License-File: LICENSE
Requires-Dist: mcp>=0.1.1
Requires-Dist: requests>=2.31.0
Requires-Dist: pypi-xmlrpc==2020.12.3
Provides-Extra: dev
Requires-Dist: black; extra == "dev"
Requires-Dist: isort; extra == "dev"
Requires-Dist: mypy; extra == "dev"
Requires-Dist: ruff; extra == "dev"
Requires-Dist: build; extra == "dev"
Requires-Dist: twine; extra == "dev"
Dynamic: license-file
